py_auto_starter/__init__.py
py_auto_starter/linux.py
py_auto_starter/mac.py
py_auto_starter/windows.py
py_auto_starter-0.0.1.dist-info/LICENSE
py_auto_starter-0.0.1.dist-info/METADATA
py_auto_starter-0.0.1.dist-info/WHEEL
py_auto_starter-0.0.1.dist-info/top_level.txt
py_auto_starter-0.0.1.dist-info/RECORD
