Metadata-Version: 2.1
Name: py-auto-starter
Version: 0.0.1
Summary: cross-platform auto start
Home-page: https://github.com/shi-hou/py-auto-starter
License: MIT
Platform: windows
Platform: macos
Platform: linux
Classifier: License :: OSI Approved :: MIT License
License-File: LICENSE
